amelie/FIELD_TYPE.py
amelie/__init__.py
amelie/_column.py
amelie/_decoder.py
amelie/_encoder.py
amelie/_protocol.py
amelie/connection.py
amelie/cursor.py
amelie/errors.py
amelie/types.py
ameliepy-0.2.1.dist-info/METADATA
ameliepy-0.2.1.dist-info/WHEEL
ameliepy-0.2.1.dist-info/top_level.txt
ameliepy-0.2.1.dist-info/RECORD
