Metadata-Version: 2.4
Name: ameliepy
Version: 0.2.1
Summary: Amelie database adapter for the Python programming language.
Requires-Python: >=3.10
Requires-Dist: requests>=2.32.5
